[
  {
    "id": "we-love-mma-60",
    "title": "We Love MMA 60",
    "time": "2022-10-08T17:00:00Z",
    "until": "2022-10-08T20:00:00Z",
    "promotion": "WLMMA",
    "sports": [
      "MMA"
    ],
    "links": [
      "https://www.welovemma.de/we-love-mma-62/"
    ],
    "broadcasters": {
      "BILD_PLUS": {
      }
    }
  },
  {
    "id": "we-love-mma-61",
    "title": "We Love MMA 61",
    "time": "2022-10-29T17:00:00Z",
    "until": "2022-10-29T20:00:00Z",
    "promotion": "WLMMA",
    "sports": [
      "MMA"
    ],
    "links": [
      "https://www.welovemma.de/we-love-mma-56/"
    ],
    "broadcasters": {
      "BILD_PLUS": {
      }
    }
  }
]