[
  {
    "id": "2pc9b",
    "time": "2022-11-10T19:30:00Z",
    "title": "TFC: Escobedo vs Cabrera - Weigh In (en Español)",
    "url": "https://www.fite.tv/watch/tfc-escobedo-vs-cabrera-weigh-in/2pc9b/",
    "price": "FREE",
    "sports": [
      "BOXING"
    ]
  },
  {
    "id": "2pc8q",
    "time": "2022-11-11T17:30:00Z",
    "title": "Probellum: Sunny Edwards vs Felix Alvarado",
    "url": "https://www.fite.tv/watch/probellum-edwards-vs-alvarado/2pc8q/",
    "price": "FREE",
    "sports": [
      "BOXING"
    ]
  },
  {
    "id": "2pc9u",
    "time": "2022-11-12T00:00:00Z",
    "title": "TFC: Escobedo vs Cabrera - Prelims",
    "url": "https://www.fite.tv/watch/tfc-escobedo-vs-cabrera-prelims/2pc9u/",
    "price": "FREE",
    "sports": [
      "BOXING"
    ]
  },
  {
    "id": "2pc92",
    "time": "2022-11-12T03:00:00Z",
    "title": "Triller Fight Club: Jonathan \"Perita\" Escobedo vs Misael Cabrera",
    "url": "https://www.fite.tv/watch/tfc-escobedo-vs-cabrera/2pc92/",
    "price": "WATCH WITH FITE+",
    "sports": [
      "BOXING"
    ]
  },
  {
    "id": "2pc8m",
    "time": "2022-11-12T06:00:00Z",
    "title": "44 Magnum Promotions #1: Ramen Habib vs Jaga Chan",
    "url": "https://www.fite.tv/watch/44-magnum-promotions-1/2pc8m/",
    "price": "$14.99",
    "sports": [
      "KICKBOXING",
      "MMA"
    ]
  },
  {
    "id": "2pc9c",
    "time": "2022-11-12T17:30:00Z",
    "title": "Alpha Fight League 2",
    "url": "https://www.fite.tv/watch/alpha-fight-league-2/2pc9c/",
    "price": "$9.99",
    "sports": [
      "MMA"
    ]
  },
  {
    "id": "2pc9p",
    "time": "2022-11-12T19:00:00Z",
    "title": "Natasha Jonas vs Marie-Eve Dicaire",
    "url": "https://www.fite.tv/watch/jonas-vs-dicaire/2pc9p/",
    "price": "$9.99",
    "sports": [
      "BOXING"
    ]
  },
  {
    "id": "2pc74",
    "time": "2022-11-13T01:00:00Z",
    "title": "Delta Fighting Championship 4: Dillon Fraley vs Josh Marsh",
    "url": "https://www.fite.tv/watch/dfc-4/2pc74/",
    "price": "$12.99",
    "sports": [
      "MMA"
    ]
  },
  {
    "id": "2pc9i",
    "time": "2022-11-13T16:00:00Z",
    "title": "Mayweather Jr. vs Deji: PreShow",
    "url": "https://www.fite.tv/watch/mayweather-jr-vs-deji-preshow/2pc9i/",
    "price": "FREE",
    "sports": [
      "BOXING"
    ]
  },
  {
    "id": "2pc6k",
    "time": "2022-11-13T18:00:00Z",
    "title": "Floyd Mayweather Jr. vs Deji",
    "url": "https://www.fite.tv/watch/mayweather-jr-vs-deji/2pc6k/",
    "price": "$19.99",
    "sports": [
      "BOXING"
    ]
  },
  {
    "id": "2pc95",
    "time": "2022-11-14T03:00:00Z",
    "title": "The Jon Fitch Knows Nothing Podcast, November 13th",
    "url": "https://www.fite.tv/watch/jon-fitch-knows-nothing-november-13/2pc95/",
    "price": "FREE",
    "sports": [
      "MMA"
    ]
  },
  {
    "id": "2pc80",
    "time": "2022-11-19T01:00:00Z",
    "title": "BKFC 33 Omaha: Prelims",
    "url": "https://www.fite.tv/watch/bkfc-33/2pc80/",
    "price": "FREE",
    "sports": [
      "BARE_KNUCKLE",
      "BOXING",
      "MMA"
    ]
  },
  {
    "id": "2pc7z",
    "time": "2022-11-19T02:00:00Z",
    "title": "BKFC 33 Omaha: Joey Beltran vs Houston Alexander",
    "url": "https://www.fite.tv/watch/bkfc-33/2pc7z/",
    "price": "$19.99",
    "sports": [
      "BARE_KNUCKLE",
      "BOXING",
      "MMA"
    ]
  },
  {
    "id": "2pc8r",
    "time": "2022-11-19T17:00:00Z",
    "title": "Mikenta Fight Night 5",
    "url": "https://www.fite.tv/watch/mikenta-fight-night-5/2pc8r/",
    "price": "$14.99",
    "sports": [
      "MMA"
    ]
  },
  {
    "id": "2pc8f",
    "time": "2022-11-20T01:00:00Z",
    "title": "Ignite: Brawl @ Bourbon Street V",
    "url": "https://www.fite.tv/watch/ignite-brawl-at-bourbon-street-5/2pc8f/",
    "price": "$24.99",
    "sports": [
      "MMA"
    ]
  },
  {
    "id": "2pc1i",
    "time": "2022-11-24T01:00:00Z",
    "title": "Rumble @ The Rabbit Hole",
    "url": "https://www.fite.tv/watch/rumble-at-the-rabbit-hole/2pc1i/",
    "price": "$10.99",
    "sports": [
      "BOXING"
    ]
  },
  {
    "id": "2pc5w",
    "time": "2022-11-26T09:30:00Z",
    "title": "Demolition Fight Series 8",
    "url": "https://www.fite.tv/watch/demolition-fight-series-8/2pc5w/",
    "price": "$9.99",
    "sports": [
      "MMA"
    ]
  },
  {
    "id": "2pbyv",
    "time": "2022-11-26T18:00:00Z",
    "title": "Gladius World Series",
    "url": "https://www.fite.tv/watch/gladius-world-series/2pbyv/",
    "price": "$9.99",
    "sports": [
      "MMA"
    ]
  },
  {
    "id": "2pc6z",
    "time": "2022-11-27T02:00:00Z",
    "title": "Jose Zepeda vs Regis Prograis",
    "url": "https://www.fite.tv/watch/zepeda-vs-prograis/2pc6z/",
    "price": "$14.99",
    "sports": [
      "BOXING"
    ]
  },
  {
    "id": "2pc97",
    "time": "2022-12-03T17:00:00Z",
    "title": "Senshi 14",
    "url": "https://www.fite.tv/watch/senshi-14/2pc97/",
    "price": "FREE",
    "sports": [
      "MMA"
    ]
  },
  {
    "id": "2pc8c",
    "time": "2022-12-03T18:00:00Z",
    "title": "Ignite: Nak Muay II",
    "url": "https://www.fite.tv/watch/ignite-nak-muay-2/2pc8c/",
    "price": "$24.99",
    "sports": [
      "MMA"
    ]
  },
  {
    "id": "2pc57",
    "time": "2022-12-03T22:00:00Z",
    "title": "Top Level Pro 9: Grappling Series",
    "url": "https://www.fite.tv/watch/top-level-pro-9/2pc57/",
    "price": "WATCH WITH FITE+",
    "sports": [
      "GRAPPLING",
      "MMA"
    ]
  },
  {
    "id": "2pc8l",
    "time": "2022-12-04T01:00:00Z",
    "title": "Ignite: Boxing I",
    "url": "https://www.fite.tv/watch/ignite-boxing-1/2pc8l/",
    "price": "$24.99",
    "sports": [
      "BOXING"
    ]
  },
  {
    "id": "2pc99",
    "time": "2022-12-04T01:00:00Z",
    "title": "SlapFight Championship 21",
    "url": "https://www.fite.tv/watch/slapfight-championship-21/2pc99/",
    "price": "WATCH WITH FITE+",
    "sports": [
      "BOXING"
    ]
  },
  {
    "id": "2pc85",
    "time": "2022-12-05T01:00:00Z",
    "title": "Subversiv Miami: Jiu-Jitsu vs MMA",
    "url": "https://www.fite.tv/watch/subversiv-jiu-jitsu-vs-mma/2pc85/",
    "price": "$16.99",
    "sports": [
      "MMA"
    ]
  },
  {
    "id": "2pbxe",
    "time": "2022-12-09T08:30:00Z",
    "title": "Senshi: Australia vs Europe",
    "url": "https://www.fite.tv/watch/senshi-australia-vs-europe/2pbxe/",
    "price": "$12.99",
    "sports": [
      "KICKBOXING",
      "MMA"
    ]
  },
  {
    "id": "2pc8z",
    "time": "2022-12-10T00:30:00Z",
    "title": "Rivalta Boxing: The Fight Before Christmas",
    "url": "https://www.fite.tv/watch/rivalta-the-fight-before-christmas/2pc8z/",
    "price": "WATCH WITH FITE+",
    "sports": [
      "BOXING"
    ]
  },
  {
    "id": "2pbo5",
    "time": "2022-12-18T07:30:00Z",
    "title": "Prince Promotions 6: Nick Atkins vs Prince Bunjaku",
    "url": "https://www.fite.tv/watch/prince-promotions-6/2pbo5/",
    "price": "$19.99",
    "sports": [
      "MMA"
    ]
  }
]