[
  {
    "id": 15520052,
    "time": "2022-05-13T01:00:00Z",
    "until": "2022-05-13T02:30:00Z",
    "url": "https://www.tvtv.de/sendung/15520052/boxen",
    "broadcaster": "Eurosport 2",
    "title": "Boxen",
    "details": [
      "Boxing",
      "Sport, Boxen 2020"
    ]
  },
  {
    "id": 15624070,
    "time": "2022-05-13T19:00:00Z",
    "until": "2022-05-13T19:30:00Z",
    "url": "https://www.tvtv.de/sendung/15624070/boxen-damen-wbc-silver-belt-bantamgewicht-cetin-voraberger-highlights-aus-istanbul",
    "broadcaster": "ORF Sport+",
    "title": "Boxen Damen WBC Silver Belt Bantamgewicht: Cetin – Voraberger, Highlights aus Istanbul",
    "details": [
      "Boxing",
      "Sport, Boxen"
    ],
    "description": "WBC Silver Belt im Bantamgewicht der Damen: Cetin – Voraberger"
  },
  {
    "id": 15848176,
    "time": "2022-05-14T20:00:00Z",
    "until": "2022-05-14T21:10:00Z",
    "url": "https://www.tvtv.de/sendung/15848176/bild-fight-night-die-gladiator-fight-night-aus-ingolstadt",
    "broadcaster": "Bild TV",
    "title": "BILD FIGHT NIGHT – Die Gladiator Fight Night aus Ingolstadt",
    "details": [
      "Sport, Boxen, D 2022"
    ],
    "description": "Die Gladiator Fight Night aus Ingolstadt"
  },
  {
    "id": 15533655,
    "time": "2022-05-14T20:45:00Z",
    "until": "2022-05-14T22:45:00Z",
    "url": "https://www.tvtv.de/sendung/15533655/sport-im-osten-boxen-live",
    "broadcaster": "MDR",
    "title": "Sport im Osten: Boxen live",
    "details": [
      "aus Magdeburg",
      "Sport im Osten",
      "Boxing",
      "Sport, Boxen 2022"
    ],
    "description": "U.a. WBO-Interkontinental-Titel im Cruisergewicht mit Roman Fress"
  },
  {
    "id": 15848178,
    "time": "2022-05-14T22:35:00Z",
    "until": "2022-05-14T23:00:00Z",
    "url": "https://www.tvtv.de/sendung/15848178/bild-fight-night-bellator-mma-aus-london",
    "broadcaster": "Bild TV",
    "title": "BILD FIGHT NIGHT – Bellator MMA aus London",
    "details": [
      "Sport, Boxen, D 2022"
    ],
    "description": "Bellator MMA aus London"
  },
  {
    "id": 15848180,
    "time": "2022-05-14T23:00:00Z",
    "until": "2022-05-15T00:10:00Z",
    "url": "https://www.tvtv.de/sendung/15848180/bild-fight-night-die-gladiator-fight-night-aus-ingolstadt",
    "broadcaster": "Bild TV",
    "title": "BILD FIGHT NIGHT – Die Gladiator Fight Night aus Ingolstadt",
    "details": [
      "Sport, Boxen, D 2022"
    ],
    "description": "Die Gladiator Fight Night aus Ingolstadt"
  },
  {
    "id": 15650120,
    "time": "2022-05-14T23:30:00Z",
    "until": "2022-05-15T00:00:00Z",
    "url": "https://www.tvtv.de/sendung/15650120/boxen-damen-wbc-silver-belt-bantamgewicht-cetin-voraberger-highlights-aus-istanbul",
    "broadcaster": "ORF Sport+",
    "title": "Boxen Damen WBC Silver Belt Bantamgewicht: Cetin – Voraberger, Highlights aus Istanbul",
    "details": [
      "Boxing",
      "Sport, Boxen"
    ],
    "description": "WBC Silver Belt im Bantamgewicht der Damen: Cetin – Voraberger"
  },
  {
    "id": 15848183,
    "time": "2022-05-15T01:20:00Z",
    "until": "2022-05-15T01:45:00Z",
    "url": "https://www.tvtv.de/sendung/15848183/bild-fight-night-bellator-mma-aus-london",
    "broadcaster": "Bild TV",
    "title": "BILD FIGHT NIGHT – Bellator MMA aus London",
    "details": [
      "Sport, Boxen, D 2022"
    ],
    "description": "Bellator MMA aus London"
  },
  {
    "id": 15651337,
    "time": "2022-05-16T15:30:00Z",
    "until": "2022-05-16T16:00:00Z",
    "url": "https://www.tvtv.de/sendung/15651337/boxen-damen-wbc-silver-belt-bantamgewicht-cetin-voraberger-highlights-aus-istanbul",
    "broadcaster": "ORF Sport+",
    "title": "Boxen Damen WBC Silver Belt Bantamgewicht: Cetin – Voraberger, Highlights aus Istanbul",
    "details": [
      "Boxing",
      "Sport, Boxen"
    ],
    "description": "WBC Silver Belt im Bantamgewicht der Damen: Cetin – Voraberger"
  },
  {
    "id": 15735984,
    "time": "2022-05-17T20:35:00Z",
    "until": "2022-05-17T22:00:00Z",
    "url": "https://www.tvtv.de/sendung/15735984/boxen",
    "broadcaster": "DAZN 2",
    "title": "Boxen",
    "details": [
      "Boxing",
      "Sport, Boxen"
    ],
    "description": "Tyson Fury – Deontay Wilder III"
  }
]