[{"id":"2023-01-one-on-prime-video-6","title":"ONE on Prime Video 6","time":"2023-01-14T01:00:00Z","until":"2023-01-14T04:00:00Z","promotion":"ONE","sports":["MMA","KICKBOXING","MUAY_THAI"],"links":["https://www.tapology.com/fightcenter/events/93660-one-on-prime-video-6"],"broadcasters":{"YOUTUBE":{"free":true}}},{"id":"2023-01-ufc-fight-night-gastelum-vs-imavov","title":"UFC Fight Night: Gastelum vs. Imavov","time":"2023-01-14T23:00:00Z","until":"2023-01-15T02:00:00Z","promotion":"UFC","sports":["MMA"],"links":["https://www.tapology.com/fightcenter/events/93279-ufc-fight-night"],"card":["Main Event: Kelvin Gastelum (17-8-0) vs. Nassourdine Imavov (12-3-0)","Prelim: Jeff Molina (11-2-0) vs. Jimmy Flick (16-5-0)"],"broadcasters":{"DAZN":{},"UFC_FIGHT_PASS":{}}},{"id":"2023-01-ufc-283","title":"UFC 283","time":"2023-01-21T23:00:00Z","until":"2023-01-22T02:00:00Z","promotion":"UFC","sports":["MMA"],"links":["https://www.tapology.com/fightcenter/events/92055-ufc-283"],"card":["Co-Main Event: Deiveson Figueiredo (21-2-1) vs. Brandon Moreno (20-6-2)","Main Card: Brad Tavares (19-7-0) vs. Gregory Rodrigues (13-4-0)","Main Card: Maurício Rua (27-13-1) vs. Ihor Potieria (18-3-0)","Prelim: Gabriel Bonfim (13-0-0) vs. Mounir Lazzez (11-2-0)","Prelim: Josiane Nunes (9-1-0) vs. Zarah Fairn (6-4-0)"],"broadcasters":{"DAZN":{},"UFC_FIGHT_PASS":{}}}]