[
  {
    "id": "night-of-the-fighters-2022-03-19",
    "promotion": "_OTHER",
    "sports": [
      "KICKBOXING"
    ],
    "tags": [
      "#Buchen"
    ],
    "mainCard": {
      "title": "Night of the Fighters",
      "time": "2022-03-19T17:00:00Z",
      "until": "2022-03-19T21:00:00Z",
      "broadcasters": {
        "FIGHT24_TV": {
          "freeAfter": 24
        }
      }
    },
    "fightEvents": {
      "id": "night-of-the-fighters",
      "time": "2022-03-19T12:00:00Z",
      "until": "2022-03-19T21:00:00Z",
      "title": "Night of the Fighters",
      "url": "https://www.fightevents.de/event/night-of-the-fighters/",
      "broadcaster": "FIGHT24_TV",
      "tags": [
        "Cameron Brunke",
        "Denis Schneider",
        "Dimitry Mechanikov",
        "Fight24.tv",
        "Hainstadt",
        "Jason Klein",
        "Jason Sakraschinsky",
        "K1",
        "Kerim Yerligül",
        "Kickboxen",
        "Marvin Grimm",
        "Nick Beschner",
        "Night of the Fighters",
        "Raua Omer",
        "Tarik Elfarra"
      ],
      "categories": [
        "Boxen",
        "Fight24.tv",
        "K1/Kickboxen",
        "Livestream",
        "MMA",
        "National"
      ]
    }
  },
  {
    "id": "bjornsson-hall-2022-03-19",
    "promotion": "_OTHER",
    "sports": [
      "BOXING"
    ],
    "tags": [
      "#ThorVsEddie",
      "#ThorEddie",
      "#BjornssonHall"
    ],
    "links": [
      "https://www.tapology.com/fightcenter/events/87752-thor-vs-eddie-heaviest-boxing-match-in-history"
    ],
    "mainCard": {
      "title": "Thor vs. Eddie: The Heaviest Boxing Match In History",
      "time": "2022-03-19T20:30:00Z",
      "until": "2022-03-19T22:30:00Z",
      "broadcasters": {
        "SEGI_TV": {
          "url": "https://www.segi.tv/thorvseddie",
          "free": true
        }
      }
    }
  },
  {
    "id": "one-man-series-2022-03-26",
    "promotion": "_OTHER",
    "sports": [
      "MMA",
      "KICKBOXING"
    ],
    "tags": [
      "#Hamburg"
    ],
    "links": [
      "https://www.fightevents.de/event/one-man-series-next-level/"
    ],
    "mainCard": {
      "title": "One Man Series – Next Level",
      "time": "2022-03-26T17:00:00Z",
      "until": "2022-03-26T21:30:00Z",
      "broadcasters": {
        "FIGHT24_TV": {
        }
      }
    },
    "fightEvents": {
      "id": "one-man-series-next-level",
      "time": "2022-03-26T17:00:00Z",
      "until": "2022-03-26T21:30:00Z",
      "title": "One Man Series – Next Level",
      "url": "https://www.fightevents.de/event/one-man-series-next-level/",
      "broadcaster": "FIGHT24_TV",
      "tags": [
        "Clement Noel",
        "Hamburg",
        "Jan Grossmann",
        "K1",
        "Milan Brandau",
        "MMA",
        "Next Level",
        "ONE MAN Series",
        "Tahir Della"
      ],
      "categories": [
        "Fight24.tv",
        "K1/Kickboxen",
        "Livestream",
        "MMA",
        "National"
      ]
    }
  },
  {
    "id": "ajp-grappling-2022-04-16-2",
    "promotion": "_OTHER",
    "sports": [
      "GRAPPLING"
    ],
    "mainCard": {
      "title": "AJP Tour Sofia",
      "time": "2022-04-16T12:00:00Z",
      "broadcasters": {
        "FITE_TV": {
          "url": "https://www.fite.tv/watch/ajp-tour-sofia-int-pro-gi-april/2payw/",
          "free": true
        }
      },
      "fite": {
        "id": "2payw",
        "time": "2022-04-16T12:00:00Z",
        "title": "AJP Tour Sofia International Pro - Gi, April 16th",
        "url": "https://www.fite.tv/watch/ajp-tour-sofia-int-pro-gi-april/2payw/",
        "price": "FREE",
        "sports": [
          "GRAPPLING",
          "MMA"
        ]
      }
    }
  },
  {
    "id": "ajp-grappling-2022-04-16",
    "promotion": "_OTHER",
    "sports": [
      "GRAPPLING"
    ],
    "mainCard": {
      "title": "AJP Tour Orlando",
      "time": "2022-04-16T19:00:00Z",
      "broadcasters": {
        "FITE_TV": {
          "url": "https://www.fite.tv/watch/ajp-tour-orlando-international-pro-g/2paw9/",
          "free": true
        }
      },
      "fite": {
        "id": "2paw9",
        "time": "2022-04-16T19:00:00Z",
        "title": "AJP Tour Orlando: International Pro - Gi",
        "url": "https://www.fite.tv/watch/ajp-tour-orlando-international-pro-g/2paw9/",
        "price": "FREE",
        "sports": [
          "GRAPPLING",
          "MMA"
        ]
      }
    }
  },
  {
    "id": "welcome-to-the-east-2022-04-23",
    "promotion": "_OTHER",
    "sports": [
      "KICKBOXING"
    ],
    "tags": [
      "#Erfurt",
      "#EM",
      "#DM",
      "#Tournament"
    ],
    "mainCard": {
      "title": "Welcome to the East 5",
      "time": "2022-04-23T14:30:00Z",
      "until": "2022-04-23T21:30:00Z",
      "broadcasters": {
        "FIGHT24_TV": {
        }
      }
    },
    "fightEvents": {
      "id": "welcome-to-the-east-5",
      "time": "2022-04-23T14:30:00Z",
      "until": "2022-04-23T21:30:00Z",
      "title": "Welcome to the East 5",
      "url": "https://www.fightevents.de/event/welcome-to-the-east-5/",
      "broadcaster": "FIGHT24_TV",
      "tags": [
        "Arthur Derksen",
        "Bijan Navabi",
        "Christoph Wunn",
        "Erfurt",
        "Fight Night",
        "Fightnight",
        "Filip Szostak",
        "Furkan Gencer",
        "Ingiohairo Kani",
        "Jan Kaffa",
        "Marian Lewin",
        "Raphael Steinbach",
        "Renato Achternaam",
        "Sergej Gavrusenko",
        "Tim Hoffmann",
        "Welcome to the East",
        "Welcome to the East 5"
      ],
      "categories": [
        "Fight24.tv",
        "K1/Kickboxen",
        "Livestream",
        "MMA",
        "National"
      ]
    }
  }
]