[
  {
    "id": "tapology-101278",
    "promotion": "BRAVE",
    "sports": [
      "MMA"
    ],
    "mainCard": {
      "hidden": true,
      "title": "BRAVE CF 72",
      "time": "2023-06-23T15:00:00Z"
    },
    "tapology": {
      "id": 101278,
      "time": "2023-06-23T15:00:00Z",
      "title": "BRAVE CF 72",
      "info": "Confirmed Upcoming MMA Event",
      "url": "https://www.tapology.com/fightcenter/events/101278-brave-cf-72",
      "sports": [
        "MMA"
      ],
      "card": [
        "Main Event: Roman Bogatov (13-1-0) vs. Nemat Abdrashitov (18-8-0)",
        "Co-Main Event: Magomed Idrisov (8-0-0) vs. B. Gavashelishvili (10-4-0)",
        "Main Card: Olzhas Eskaraev (14-6-0) vs. Ylies Djiroun (18-7-0)",
        "Main Card: Yanis Ghemmouri (11-1-0) vs. Mehmosh Raza (10-5-0)",
        "Prelim: Rasul Magomedov (0-0-0) vs. Mohamed Hisham Baraka (1-0-0)",
        "Prelim: Eliezer Kubanza (3-0-0) vs. Rayan Atmani (3-0-0)",
        "Prelim: Mohamed Alsameea (0-0-0) vs. Ibrahim Hassan (2-2-0)",
        "Prelim: Mohammadseifi Mohsen (2-2-0) vs. Noor El Islam (1-1-0)"
      ],
      "links": [
        "http://www.sherdog.com/events/brave-cf-72-brave-combat-federation-72-97920",
        "https://events.mixedmartialarts.com/brave-cf-72:6d03880a-84f3-4a90-b680-9ef5fe31d18f"
      ]
    }
  },
  {
    "id": "tapology-102416",
    "promotion": "BRAVE",
    "sports": [
      "MMA"
    ],
    "mainCard": {
      "hidden": true,
      "title": "BRAVE CF 73",
      "time": "2023-08-12T23:00:00Z"
    },
    "tapology": {
      "id": 102416,
      "time": "2023-08-12T23:00:00Z",
      "title": "BRAVE CF 73",
      "info": "Confirmed Upcoming MMA Event",
      "url": "https://www.tapology.com/fightcenter/events/102416-brave-cf-73",
      "sports": [
        "MMA"
      ],
      "card": [
        "Main Event: Jose Torres (11-1-1) vs. Nkosi Ndebele (6-1-0)"
      ]
    }
  }
]