[
  {
    "id": "tapology-97870",
    "promotion": "CES",
    "sports": [
      "MMA"
    ],
    "tags": [
      "#CES72"
    ],
    "mainCard": {
      "title": "CES 72: Caron vs. Collins",
      "time": "2023-03-19T00:00:00Z",
      "broadcasters": {
        "UFC_FIGHT_PASS": {
        }
      }
    },
    "tapology": {
      "id": 97870,
      "time": "2023-03-19T00:00:00Z",
      "title": "CES 72: Caron vs. Collins",
      "info": "Confirmed Upcoming MMA Event",
      "url": "https://www.tapology.com/fightcenter/events/97870-ces-72",
      "sports": [
        "MMA"
      ],
      "card": [
        "Main Event: Tim Caron (12-5-0) vs. Fran Collins (4-0-0)",
        "Co-Main Event: Nathan Ghareeb (7-2-0) vs. Damion Nelson (4-1-0)",
        "Main Card: Justin Valentin (3-2-0) vs. Tim Flores (3-1-0)",
        "Main Card: Harris Bonfiglio (5-1-0) vs. Giorgi Kudukhashvili (5-4-0)",
        "Main Card: Mike Kimbel (4-3-0) vs. Daniel Arriaga (0-2-0)",
        "Prelim: Tristan Turano (2-1-0) vs. Cullen Johnson (3-1-0)"
      ],
      "links": [
        "https://events.mixedmartialarts.com/ces-72:e50dd4b1-3c0c-4b6a-80af-263a4d2e2736"
      ]
    }
  }
]