[
  {
    "id": "tapology-90496",
    "promotion": "CFFC",
    "sports": [
      "MMA"
    ],
    "tags": [
      "#CFFC112"
    ],
    "mainCard": {
      "title": "Cage Fury FC 112: Perez vs. Wells",
      "time": "2022-08-27T00:00:00Z",
      "broadcasters": {
        "UFC_FIGHT_PASS": {
        }
      },
      "fightPass": {
        "id": 221240,
        "time": "2022-08-27T00:00:00Z",
        "title": "Cage Fury FC 112"
      }
    },
    "tapology": {
      "id": 90496,
      "time": "2022-08-26T22:00:00Z",
      "title": "CFFC 112: Perez vs. Wells",
      "info": "Confirmed Upcoming MMA Event",
      "url": "https://www.tapology.com/fightcenter/events/90496-cffc-112",
      "sports": [
        "MMA"
      ],
      "card": [
        "Main Event: Frank Wells (3-1-0) vs. Jose Perez (6-1-0)",
        "Main Card: James Clarke (6-3-0) vs. Aaron La Farge (5-2-0)",
        "Main Card: Eric Nolan (1-1-0) vs. Ibrahim Kallie (1-1-0)",
        "Main Card: Elijah Humes (1-0-0) vs. Thomas Picciano (1-0-0)",
        "Main Card: Marcus Leach II (1-0-0) vs. Ian Allston (1-0-0)",
        "Main Card: Angel Pacheco (6-1-0) vs. Vilson Ndregjoni (5-2-0)",
        "Main Card: Riley Palmer (4-0-0) vs. Steve Phelan (7-3-0)",
        "Main Card: Luke Fernandez (5-0-0) vs. Reeves Davis Jr. (8-1-0)",
        "Main Card: Xhelal Lleshi (3-0-0) vs. Bilal Hasan (6-0-0)",
        "Prelim: Edwin Smart (3-4-0) vs. Alex Myers (2-2-0)",
        "Prelim: Ty Miller (2-0-0) vs. Manny Morales (1-0-0)",
        "Prelim: Keron Reed (0-0-0) vs. Kelvin Sterling (0-0-0)"
      ],
      "links": [
        "http://www.sherdog.com/events/cffc-112-cage-fury-fighting-championships-112-93831",
        "https://events.mixedmartialarts.com/cffc-112:85ae9ed4-ff8b-4a9c-a55c-34c1faef3af2",
        "https://www.bestfightodds.com/events/cffc-112-2628"
      ]
    }
  },
  {
    "id": "tapology-90497",
    "promotion": "CFFC",
    "sports": [
      "GRAPPLING"
    ],
    "mainCard": {
      "title": "Fury Pro Grappling 5",
      "time": "2022-08-28T00:00:00Z",
      "broadcasters": {
        "UFC_FIGHT_PASS": {
        }
      },
      "fightPass": {
        "id": 221244,
        "time": "2022-08-28T00:00:00Z",
        "title": "Fury Pro Grappling 5"
      }
    },
    "tapology": {
      "id": 90497,
      "time": "2022-08-27T21:00:00Z",
      "title": "Fury Pro Grappling 5",
      "info": "Confirmed Upcoming Grappling Event",
      "url": "https://www.tapology.com/fightcenter/events/90497-fury-pro-grappling-5",
      "sports": [
        "GRAPPLING"
      ],
      "card": [
        "Main Event: Clay Guida vs. Alex Caceres",
        "Co-Main Event: Eryk Anders vs. Andre Petroski",
        "Main Card: Connor Dixon vs. Jonathan Piersma",
        "Main Card: Eddy Torres vs. Mike Medrano",
        "Main Card: Patrick Brady vs. Brian Sheehan",
        "Main Card: Jason Guida vs. John Mabrey",
        "Main Card: Sean Yadimarco vs. Charlie Livingston",
        "Main Card: Andrew Kochel vs. Matt Ferraiolo",
        "Main Card: Jon Pellot vs. Luis Carreras",
        "Main Card: Regis Farias vs. Mike Padilla",
        "Main Card: Max Livingston vs. Michael Villeneuve",
        "Main Card: Chris Dempsey vs. Daishi Goto",
        "Main Card: Rey De Leon vs. Kevin Dantzler",
        "Prelim: Nicholas Willey vs. Robbie De La Rionda",
        "Prelim: Ty Costlow vs. Christian Hannigan",
        "Prelim: Thom O'Hara vs. Ali Eslami",
        "Prelim: Tim Ball vs. Kevin Stilo",
        "Prelim: Alexandria Whitlock vs. Valerie Martinez",
        "Prelim: Jonna Wood vs. Chrissy Briggs",
        "Prelim: Chris Emery vs. Luke Staley",
        "Prelim: Amanda Mazza vs. Angelina Hernandez"
      ]
    }
  }
]