[
  {
    "id": "tapology-89059",
    "promotion": "CWFC",
    "sports": [
      "MMA"
    ],
    "tags": [
      "#CW141"
    ],
    "mainCard": {
      "title": "Cage Warriors 141: Driscoll vs. Hardwick",
      "time": "2022-07-22T20:00:00Z",
      "broadcasters": {
        "UFC_FIGHT_PASS": {
        }
      },
      "fightPass": {
        "id": 219523,
        "time": "2022-07-22T20:00:00Z",
        "title": "Cage Warriors 141"
      }
    },
    "prelims": {
      "title": "Cage Warriors 141: Prelims",
      "time": "2022-07-22T17:30:00Z",
      "broadcasters": {
        "UFC_FIGHT_PASS": {
        }
      },
      "fightPass": {
        "id": 219522,
        "time": "2022-07-22T17:30:00Z",
        "title": "Cage Warriors 141 Prelims"
      }
    },
    "tapology": {
      "id": 89059,
      "time": "2022-07-22T16:30:00Z",
      "title": "Cage Warriors 141: Driscoll vs. Hardwick",
      "titleAlt": "CW 141",
      "info": "Confirmed Upcoming MMA Event",
      "url": "https://www.tapology.com/fightcenter/events/89059-cage-warriors-141",
      "sports": [
        "MMA"
      ],
      "card": [
        "Main Event: Kyle Driscoll (13-3-0) vs. George Hardwick (9-1-0)",
        "Main Card: Jim Wallhead (31-11-0) vs. Daniel Skibiński (18-7-0)",
        "Main Card: Agy Sardari (15-3-0) vs. Mike Figlak (7-0-0)",
        "Main Card: Mick Stanton (8-6-0) vs. Darren Stewart (12-8-0)",
        "Main Card: Samuel Bark (4-1-0) vs. Tobias Harila (10-2-0)",
        "Prelim: Jeremy Petley (14-9-1) vs. Steve Aimable (17-8-0)",
        "Prelim: Reece McEwan (4-1-0) vs. Kingsley Crawford (8-3-0)",
        "Prelim: Naglis Kanišauskas (5-1-0) vs. Will Currie (7-2-0)",
        "Prelim: Sam Spencer (6-3-0) vs. Adam Amarasinghe (6-3-0)",
        "Prelim: Jesse Urholin (8-0-0) vs. Madars Fleminas (9-3-0)",
        "Prelim: Ander Sanchez (1-0-0) vs. Lone'er Kavanagh (3-0-0)",
        "Prelim: Alexander Lindgren (3-1-0) vs. Omiel Brown (3-1-0)"
      ],
      "links": [
        "http://www.sherdog.com/events/cw-141-cage-warriors-141-92917",
        "https://events.mixedmartialarts.com/cage-warriors-141:90da1ddd-a6d6-48fb-afc3-6097f62fa4f9",
        "https://cagewarriors.com/cw-141-london-22nd-july/",
        "https://www.bestfightodds.com/events/cage-warriors-141-2596"
      ]
    }
  }
]