[
  {
    "id": "tapology-90884",
    "promotion": "FUSION",
    "sports": [
      "MMA"
    ],
    "mainCard": {
      "hidden": true,
      "title": "Fusion Fight League: Lights Out at the Dome 5",
      "time": "2022-08-28T01:00:00Z",
      "broadcasters": {
        "UFC_FIGHT_PASS": {
        }
      }
    },
    "tapology": {
      "id": 90884,
      "time": "2022-08-28T01:00:00Z",
      "title": "Fusion Fight League: Lights Out at the Dome 5",
      "info": "Confirmed Upcoming MMA Event",
      "url": "https://www.tapology.com/fightcenter/events/90884-fusion-fight-league-lights-out-at-the-dome",
      "sports": [
        "MMA"
      ],
      "card": [
        "Main Card: Dre Coles (4-0-0) vs. Mitch Wiles (4-3-0)"
      ]
    }
  }
]