[
  {
    "id": "tapology-104784",
    "promotion": "LFL_NL",
    "sports": [
      "MMA"
    ],
    "mainCard": {
      "hidden": true,
      "title": "LFL New Talent 6",
      "time": "2023-10-29T14:00:00Z"
    },
    "tapology": {
      "id": 104784,
      "time": "2023-10-29T14:00:00Z",
      "title": "LFL New Talent 6",
      "info": "Confirmed Upcoming MMA Event",
      "url": "https://www.tapology.com/fightcenter/events/104784-lfl-new-talent-6",
      "sports": [
        "MMA"
      ],
      "card": [
        "Main Event: Kamil Puchalski (2-3-0) vs. Stefano Groenendaal (3-1-0)",
        "Main Card: Jaleesa Alfons (0-1-0) vs. Daan van Hassel (1-0-0)",
        "Main Card: Luuk Valk (2-1-0) vs. Jakub Adwent (3-2-0)",
        "Main Card: Anthony Isidahomen (1-1-0) vs. Mohammad Al Ghamri (1-0-1)",
        "Main Card: Mahdi Mohammadi (3-3-3) vs. Gideon Hiwat (0-2-0)",
        "Main Card: Victor Gomez Zabala (2-2-1) vs. Nordin Amani (1-1-0)",
        "Main Card: Jules Bruno (1-1-1) vs. Almyrando Chantre (2-1-0)",
        "Main Card: Sarah Göbel (0-0-0) vs. Kelley Hamming (1-2-0)",
        "Main Card: Thomas Nikkels (1-1-0) vs. Jahfaro Gezius (1-0-0)",
        "Main Card: Tom Molenaar (0-2-0) vs. Ruben Martis (0-0-0)"
      ]
    }
  },
  {
    "id": "tapology-104156",
    "promotion": "LFL_NL",
    "sports": [
      "MMA"
    ],
    "mainCard": {
      "hidden": true,
      "title": "Levels Fight League 10",
      "time": "2023-10-29T17:00:00Z"
    },
    "tapology": {
      "id": 104156,
      "time": "2023-10-29T17:00:00Z",
      "title": "Levels Fight League 10",
      "info": "Confirmed Upcoming MMA Event",
      "url": "https://www.tapology.com/fightcenter/events/104156-levels-fight-league-10",
      "sports": [
        "MMA"
      ],
      "card": [
        "Main Event: Mario Pinto (6-0-0) vs. Raphael Pessoa (10-5-0)",
        "Co-Main Event: Yousri Belgaroui (5-3-0) vs. Nathias Frederick (9-3-1)",
        "Main Card: Clyde Brunswijk (1-1-0) vs. Kevin Ward (0-1-0)",
        "Main Card: Mohamed Tini (4-0-0) vs. Patryk Molka (5-5-0)",
        "Main Card: Nika Tchikhinachvili (0-1-0) vs. Tayron Chavarro (2-4-0)",
        "Main Card: Noach Blyden (2-1-0) vs. Guilherme Assis (1-2-0)",
        "Main Card: Ali Popescu (0-0-0) vs. Arman Raisi (0-1-0)",
        "Main Card: Shah Kamali (0-0-0) vs. Jimmy van Bemmelen (0-3-0)"
      ]
    }
  }
]