[
  {
    "id": "tapology-85970",
    "promotion": "ONE",
    "sports": [
      "MMA",
      "MUAY_THAI"
    ],
    "tags": [
      "#ONELightsOut"
    ],
    "mainCard": {
      "title": "ONE Championship: Lights Out",
      "time": "2022-03-11T13:30:00Z",
      "broadcasters": {
        "YOUTUBE": {
          "free": true
        }
      }
    },
    "tapology": {
      "id": 85970,
      "time": "2022-03-11T13:30:00Z",
      "title": "ONE Championship: Lights Out",
      "info": "Confirmed Upcoming MMA & Muay Thai Event",
      "url": "https://www.tapology.com/fightcenter/events/85970-one-championship",
      "sports": [
        "MMA",
        "MUAY_THAI"
      ],
      "card": [
        "Main Event: Thanh Le (12-2-0) vs. Garry Tonon (6-0-0)",
        "Co-Main Event: Bibiano Fernandes (24-4-0) vs. John Lineker (34-9-0)",
        "Main Card: Prajanchai PK Saenchai vs. Joseph Lasiri"
      ],
      "links": [
        "http://www.sherdog.com/events/one-championship-lights-out-91597",
        "https://events.mixedmartialarts.com/one-championship:f5b74d79-83cb-4576-9929-d505b423b4a8"
      ]
    }
  },
  {
    "id": "tapology-85971",
    "promotion": "ONE",
    "sports": [
      "MMA",
      "KICKBOXING",
      "MUAY_THAI"
    ],
    "tags": [
      "#ONEX"
    ],
    "mainCard": {
      "title": "ONE Championship: One X",
      "time": "2022-03-26T12:30:00Z",
      "broadcasters": {
        "YOUTUBE": {
          "free": true
        }
      }
    },
    "tapology": {
      "id": 85971,
      "time": "2022-03-26T12:30:00Z",
      "title": "ONE Championship: One X",
      "info": "Confirmed Upcoming MMA, Kickboxing, & Muay Thai Event",
      "url": "https://www.tapology.com/fightcenter/events/85971-one-championship",
      "sports": [
        "MMA",
        "KICKBOXING",
        "MUAY_THAI"
      ],
      "card": [
        "Main Event: Stamp Fairtex (8-1-0) vs. Angela Lee (10-2-0)",
        "Co-Main Event: Adriano Moraes (19-3-0) vs. Yuya Wakamatsu (15-4-0)",
        "Main Card: Demetrious Johnson vs. Rodtang Jitmuangnon",
        "Main Card: Seo Hee Ham (24-8-0) vs. Denice Zamboanga (8-1-0)",
        "Main Card: Nieky Holzken vs. Islam Murtazaev",
        "Main Card: Chingiz Allazov vs. S. Sitsongpeenong",
        "Main Card: Nong-O Gaiyanghadao vs. Alaverdi Ramazanov",
        "Main Card: Amir Khan (13-8-0) vs. Ryogo Takahashi (14-5-0)",
        "Main Card: Jeremy Miado (10-4-0) vs. Lito Adiwang (13-4-0)",
        "Main Card: Capitan Petchyindee vs. Hiroki Akimoto",
        "Main Card: Eduard Folayang vs. Wayne Parr",
        "Main Card: Shinya Aoki (47-9-0) vs. Yoshihiro Akiyama (15-7-0)"
      ]
    }
  },
  {
    "id": "tapology-87416",
    "promotion": "ONE",
    "sports": [
      "KICKBOXING"
    ],
    "tags": [
      "#ONEReloaded"
    ],
    "mainCard": {
      "title": "ONE Championship: Reloaded",
      "time": "2022-04-08T09:00:00Z",
      "broadcasters": {
        "YOUTUBE": {
          "free": true
        }
      }
    },
    "tapology": {
      "id": 87416,
      "time": "2022-04-08T09:00:00Z",
      "title": "ONE Championship: Reloaded",
      "info": "Confirmed Upcoming Kickboxing Event",
      "url": "https://www.tapology.com/fightcenter/events/87416-one-championship-reloaded",
      "sports": [
        "KICKBOXING"
      ],
      "card": [
        "Main Event: Regian Eersel vs. Arian Sadiković"
      ]
    }
  }
]