[
  {
    "id": "tapology-101643",
    "promotion": "ONE",
    "sports": [
      "MMA",
      "KICKBOXING",
      "MUAY_THAI"
    ],
    "tags": [
      "#ONEFridayFights",
      "#ONEFridayFights19"
    ],
    "mainCard": {
      "title": "ONE Friday Fights 19",
      "time": "2023-06-02T12:30:00Z",
      "broadcasters": {
        "YOUTUBE": {
          "url": "https://www.youtube.com/watch?v=q0DDri1LpxE",
          "free": true
        }
      }
    },
    "tapology": {
      "id": 101643,
      "time": "2023-06-02T12:30:00Z",
      "title": "ONE Friday Fights 19",
      "info": "Confirmed Upcoming Muay Thai, MMA, & Kickboxing Event",
      "url": "https://www.tapology.com/fightcenter/events/101643-one-friday-fights-19",
      "sports": [
        "MMA",
        "KICKBOXING",
        "MUAY_THAI"
      ],
      "card": [
        "Main Event: K. Sor.Jor.Piek Uthai vs. Ilyas Musaev",
        "Co-Main Event: Ronachai Tor.Ramintra vs. A. Sor. Samarngarment",
        "Main Card: R. SidChefBoontham vs. Jalill Barnes",
        "Main Card: D. Sitnayoktaweeptaphong vs. Petchrapa Sor.Sopit",
        "Main Card: KohTao Petchsomnuek vs. Amnatdet Sitnayokmot",
        "Main Card: Panphet Sanfannatawee vs. Soroush Akbari",
        "Main Card: K. P.K. Saenchai Muaythaigym vs. Elbrus Osmanov",
        "Main Card: P. Lukjaomaesaiwaree vs. Ferzan Çiçek",
        "Main Card: P. Sor Jor Wichitpadriew vs. Noelisson Silva",
        "Main Card: Natalya Dyachkova vs. Lena Nocker",
        "Main Card: Rui Chen (15-5-0) vs. Drex Zamboanga (14-5-0)",
        "Main Card: Murad Umachiev (2-0-0) vs. Ibragim Shaymanov (5-4-0)"
      ],
      "links": [
        "http://www.sherdog.com/events/one-championship-one-friday-fights-19-97974",
        "https://events.mixedmartialarts.com/one-friday-fights-19:625e3d50-94e8-4a4e-8c9e-005698583b42"
      ]
    }
  },
  {
    "id": "tapology-100343",
    "promotion": "ONE",
    "sports": [
      "MMA",
      "KICKBOXING",
      "MUAY_THAI"
    ],
    "tags": [
      "#ONEFightNight",
      "#ONEFightNight11"
    ],
    "mainCard": {
      "title": "ONE Fight Night 11: Eersel vs. Menshikov",
      "time": "2023-06-10T00:00:00Z",
      "broadcasters": {
        "YOUTUBE": {
          "url": "https://www.youtube.com/watch?v=9ccANod0pSE",
          "free": true
        }
      }
    },
    "tapology": {
      "id": 100343,
      "time": "2023-06-09T23:00:00Z",
      "title": "ONE Fight Night 11: Eersel vs. Menshikov",
      "titleAlt": "ONE on Prime Video 11",
      "info": "Confirmed Upcoming Combat Sports Event",
      "url": "https://www.tapology.com/fightcenter/events/100343-one-fight-night-11",
      "card": [
        "Main Event: Regian Eersel vs. Dmitry Menshikov",
        "Co-Main Event: Kade Ruotolo vs. Tommy Langaker",
        "Main Card: Ilya Freymanov (11-2-0) vs. S. Zoltsetseg (6-3-0)",
        "Main Card: Superbon Singha Mawynn vs. Tayfun Özcan",
        "Main Card: Mansur Malachiev (10-0-0) vs. Jeremy Miado (10-4-0)",
        "Main Card: Nieky Holzken vs. Arian Sadiković",
        "Main Card: Artem Belakh (10-2-0) vs. Won Il Kwon (12-4-0)",
        "Main Card: Martine Michieletto vs. Amber Kitchen",
        "Main Card: Yong Hu (10-4-0) vs. Sung Hoon Woo (10-3-0)",
        "Main Card: Rade Opačić vs. Guto Inocente"
      ]
    }
  },
  {
    "id": "tapology-101567",
    "promotion": "ONE",
    "sports": [
      "MMA",
      "MUAY_THAI"
    ],
    "mainCard": {
      "title": "ONE Friday Fights 22: Bhullar vs. Malykhin",
      "time": "2023-06-23T12:30:00Z",
      "broadcasters": {
        "YOUTUBE": {
          "free": true
        }
      }
    },
    "tapology": {
      "id": 101567,
      "time": "2023-06-23T12:30:00Z",
      "title": "ONE Friday Fights 22: Bhullar vs. Malykhin",
      "info": "Confirmed Upcoming MMA & Muay Thai Event",
      "url": "https://www.tapology.com/fightcenter/events/101567-one-friday-fights-22-bhullar-vs-malykhin",
      "sports": [
        "MMA",
        "MUAY_THAI"
      ],
      "card": [
        "Main Event: Arjan Bhullar (11-1-0) vs. Anatoly Malykhin (12-0-0)",
        "Main Card: Prajanchai PK Saenchai vs. Sam-A Gaiyanghadao",
        "Main Card: Muangthai PK Saenchai (0-0-0) vs. Nico Carrillo (0-0-0)",
        "Main Card: Jomhod Sermpornwiwat (0-0-0) vs. Akram Hamidi (0-0-0)",
        "Main Card: Saeksan Or Kwanmuang (0-0-0) vs. Nathan Bendon (0-0-0)"
      ]
    }
  },
  {
    "id": "tapology-100718",
    "promotion": "ONE",
    "sports": [
      "MMA"
    ],
    "mainCard": {
      "title": "ONE Fight Night 12: Kai vs. Le 2",
      "time": "2023-07-15T00:00:00Z",
      "broadcasters": {
        "YOUTUBE": {
          "free": true
        }
      }
    },
    "tapology": {
      "id": 100718,
      "time": "2023-07-15T00:00:00Z",
      "title": "ONE Fight Night 12: Kai vs. Le 2",
      "info": "Confirmed Upcoming MMA Event",
      "url": "https://www.tapology.com/fightcenter/events/100718-one-fight-night-12-kai-vs-le-2",
      "sports": [
        "MMA"
      ],
      "card": [
        "Main Event: Kai Tang (15-2-0) vs. Thanh Le (13-3-0)"
      ]
    }
  }
]