[
  {
    "id": "tapology-88967",
    "promotion": "UFC",
    "sports": [
      "MMA"
    ],
    "tags": [
      "#UFCParis",
      "🎙@MarkBergmann",
      "🎙@SweepTheLeg1983"
    ],
    "mainCard": {
      "title": "UFC Paris: Gane vs. Tuivasa",
      "time": "2022-09-03T19:00:00Z",
      "broadcasters": {
        "DAZN": {
        },
        "UFC_FIGHT_PASS": {
        }
      },
      "fightPass": {
        "id": 222695,
        "time": "2022-09-03T19:00:00Z",
        "title": "UFC Fight Night: Gane vs Tuivasa"
      },
      "dazn": {
        "id": "napnds0i5kqq17s3vo2vm4c2k",
        "time": "2022-09-03T16:00:00Z",
        "title": "UFC Fight Night: Gane vs Tuivasa (Vor- und Hauptkämpfe)",
        "sport": "MMA",
        "competition": "UFC",
        "description": "Fight Night in der französischen Hauptstadt! In der Accor Arena in Paris treten im Rahmen der Main Card zwölf Kämpfer in sechs Kämpfen gegeneinander an. Das Highlight des Abends ist aber das Duell zweier Schwergewichte: Der Franzose Ciryl Gane hat einen Record von 11-1 und musste sich in seiner Karriere bisher nur Francis Ngannou geschlagen geben. Nun geht´s gegen den Australier Tai Tuvasa, dessen Record mit 14-3 nahezu genauso beeindruckend ist. // Kommentator: Mark Bergmann / Experte: Elias Stefanescu"
      }
    },
    "prelims": {
      "title": "UFC Paris: Prelims",
      "time": "2022-09-03T16:00:00Z",
      "broadcasters": {
        "DAZN": {
        },
        "UFC_FIGHT_PASS": {
        }
      },
      "fightPass": {
        "id": 222692,
        "time": "2022-09-03T16:00:00Z",
        "title": "UFC Fight Night: Gane vs Tuivasa Prelims"
      },
      "dazn": {
        "id": "napnds0i5kqq17s3vo2vm4c2k",
        "time": "2022-09-03T16:00:00Z",
        "title": "UFC Fight Night: Gane vs Tuivasa (Vor- und Hauptkämpfe)",
        "sport": "MMA",
        "competition": "UFC",
        "description": "Fight Night in der französischen Hauptstadt! In der Accor Arena in Paris treten im Rahmen der Main Card zwölf Kämpfer in sechs Kämpfen gegeneinander an. Das Highlight des Abends ist aber das Duell zweier Schwergewichte: Der Franzose Ciryl Gane hat einen Record von 11-1 und musste sich in seiner Karriere bisher nur Francis Ngannou geschlagen geben. Nun geht´s gegen den Australier Tai Tuvasa, dessen Record mit 14-3 nahezu genauso beeindruckend ist. // Kommentator: Mark Bergmann / Experte: Elias Stefanescu"
      }
    },
    "tapology": {
      "id": 88967,
      "time": "2022-09-03T16:00:00Z",
      "title": "UFC Fight Night: Gane vs. Tuivasa",
      "titleAlt": "UFC Fight Night Paris",
      "info": "Confirmed Upcoming MMA Event",
      "url": "https://www.tapology.com/fightcenter/events/88967-ufc-fight-night",
      "sports": [
        "MMA"
      ],
      "card": [
        "Main Event: Ciryl Gane (10-1-0) vs. Tai Tuivasa (15-3-0)",
        "Co-Main Event: Robert Whittaker (23-6-0) vs. Marvin Vettori (18-4-1)",
        "Main Card: Alessio Di Chirico (13-6-0) vs. Roman Kopylov (8-2-0)",
        "Main Card: Nasrat Haqparast (13-5-0) vs. John Makdessi (18-7-0)",
        "Main Card: William Gomis (10-2-0) vs. Jarno Errens (13-3-1)",
        "Main Card: Charles Jourdain (13-5-1) vs. Nathaniel Wood (18-5-0)",
        "Prelim: Dustin Stoltzfus (14-4-0) vs. Abusupiyan Magomedov (24-4-1)",
        "Prelim: Fares Ziam (12-4-0) vs. Michal Figlak (8-0-0)",
        "Prelim: Nassourdine Imavov (11-3-0) vs. Joaquin Buckley (15-4-0)",
        "Prelim: Benoit Saint-Denis (9-1-0) vs. Gabriel Miranda (16-5-0)",
        "Prelim: Khalid Taha (13-4-0) vs. Cristian Quiñonez (16-3-0)",
        "Prelim: Ailin Perez (7-1-0) vs. Stephanie Egger (7-3-0)"
      ],
      "links": [
        "http://www.sherdog.com/events/ufc-fight-night-209-gane-vs-tuivasa-93036",
        "http://en.wikipedia.org/wiki/UFC_Fight_Night:_Gane_vs._Tuivasa",
        "https://events.mixedmartialarts.com/ufc-fight-night:8e18d25a-304c-4fbe-bf22-fe5fa39e408b",
        "https://www.ufc.com/event/ufc-fight-night-september-03-2022",
        "http://www.ufcstats.com/event-details/00a905a4a4a2b071",
        "https://www.bestfightodds.com/events/ufc-fight-night-gane-vs-tuivasa-2518"
      ]
    }
  },
  {
    "id": "tapology-89492",
    "promotion": "UFC",
    "sports": [
      "MMA"
    ],
    "tags": [
      "#UFC279"
    ],
    "mainCard": {
      "title": "UFC 279: Chimaev vs. Diaz",
      "time": "2022-09-11T02:00:00Z",
      "broadcasters": {
        "DAZN": {
        },
        "UFC_FIGHT_PASS": {
        }
      },
      "fightPass": {
        "id": 222607,
        "time": "2022-09-11T02:00:00Z",
        "title": "UFC 279: Chimaev vs Diaz"
      },
      "dazn": {
        "id": "1icpc541b6ksh1efv86u2ytk3n",
        "time": "2022-09-11T02:00:00Z",
        "title": "UFC 279: Chimaev vs Diaz (Hauptkämpfe)",
        "sport": "MMA",
        "competition": "UFC"
      }
    },
    "prelims": {
      "title": "UFC 279: Prelims",
      "time": "2022-09-11T00:00:00Z",
      "broadcasters": {
        "UFC_FIGHT_PASS": {
        }
      },
      "fightPass": {
        "id": 222742,
        "time": "2022-09-11T00:00:00Z",
        "title": "UFC 279: Prelims"
      }
    },
    "earlyPrelims": {
      "title": "UFC 279: Early Prelims",
      "time": "2022-09-10T22:00:00Z",
      "broadcasters": {
        "UFC_FIGHT_PASS": {
        }
      },
      "fightPass": {
        "id": 222741,
        "time": "2022-09-10T22:00:00Z",
        "title": "UFC 279: Fight Pass Prelims"
      }
    },
    "tapology": {
      "id": 89492,
      "time": "2022-09-10T22:00:00Z",
      "title": "UFC 279: Chimaev vs. Diaz",
      "info": "Confirmed Upcoming MMA Event",
      "url": "https://www.tapology.com/fightcenter/events/89492-ufc-fight-night",
      "sports": [
        "MMA"
      ],
      "card": [
        "Main Event: Khamzat Chimaev (11-0-0) vs. Nate Diaz (20-13-0)",
        "Co-Main Event: Jingliang Li (19-7-0) vs. Tony Ferguson (25-7-0)",
        "Main Card: Irene Aldana (13-6-0) vs. Macy Chiasson (8-2-0)",
        "Main Card: Johnny Walker (18-7-0) vs. Ion Cutelaba (16-7-1)",
        "Main Card: Kevin Holland (23-7-0) vs. Daniel Rodriguez (16-2-0)",
        "Prelim: Norma Dumont (7-2-0) vs. Danyelle Wolf (1-0-0)",
        "Prelim: Jamie Pickett (13-7-0) vs. Denis Tiuliulin (10-6-0)",
        "Prelim: Chad Anheliger (12-5-0) vs. Heili Alateng (15-8-2)",
        "Prelim: Elise Reed (5-2-0) vs. Melissa Martinez (7-0-0)",
        "Prelim: Jake Collier (13-7-0) vs. Chris Barnett (22-8-0)",
        "Prelim: Hakeem Dawodu (13-2-1) vs. Julian Erosa (27-9-0)",
        "Prelim: Darian Weeks (5-2-0) vs. Yohan Lainesse (8-1-0)",
        "Prelim: Jailton Almeida (16-2-0) vs. Anton Turkalj (8-0-0)"
      ]
    }
  },
  {
    "id": "tapology-90191",
    "promotion": "UFC",
    "sports": [
      "MMA"
    ],
    "mainCard": {
      "title": "UFC Fight Night: Sandhagen vs. Song",
      "time": "2022-09-17T23:00:00Z",
      "broadcasters": {
        "DAZN": {
        },
        "UFC_FIGHT_PASS": {
        }
      },
      "fightPass": {
        "id": 223356,
        "time": "2022-09-17T23:00:00Z",
        "title": "UFC Fight Night: Sandhagen vs Song"
      },
      "dazn": {
        "id": "11om2oaufjmvg1bv2t2atpnvq4",
        "time": "2022-09-17T23:00:00Z",
        "title": "UFC Fight Night: Sandhagen vs Song (Hauptkämpfe)",
        "sport": "MMA",
        "competition": "UFC"
      }
    },
    "prelims": {
      "title": "UFC Fight Night: Prelims",
      "time": "2022-09-17T20:00:00Z",
      "broadcasters": {
        "UFC_FIGHT_PASS": {
        }
      },
      "fightPass": {
        "id": 223355,
        "time": "2022-09-17T20:00:00Z",
        "title": "UFC Fight Night: Sandhagen vs Song Prelims"
      }
    },
    "tapology": {
      "id": 90191,
      "time": "2022-09-17T20:00:00Z",
      "title": "UFC Fight Night: Sandhagen vs. Song",
      "info": "Confirmed Upcoming MMA Event",
      "url": "https://www.tapology.com/fightcenter/events/90191-ufc-fight-night",
      "sports": [
        "MMA"
      ],
      "card": [
        "Main Event: Cory Sandhagen (14-4-0) vs. Yadong Song (19-6-1)",
        "Co-Main Event: Giga Chikadze (14-3-0) vs. Sodiq Yusuff (12-2-0)",
        "Main Card: Chidi Njokuani (22-7-0) vs. Gregory Rodrigues (12-4-0)",
        "Main Card: Tanner Boser (20-8-1) vs. Rodrigo Nascimento (8-1-0)",
        "Main Card: Aspen Ladd (9-3-0) vs. Sara McMann (13-6-0)",
        "Main Card: Andre Fili (21-9-0) vs. Bill Algeo (16-6-0)",
        "Prelim: Trey Ogden (15-5-0) vs. Daniel Zellhuber (12-0-0)",
        "Prelim: Nikolas Motta (12-4-0) vs. Cameron VanCamp (15-6-1)",
        "Prelim: Trevin Giles (14-4-0) vs. Louis Cosce (7-1-0)",
        "Prelim: Damon Jackson (21-4-1) vs. Pat Sabatini (17-3-0)",
        "Prelim: Loma Lookboonmee (6-3-0) vs. Diana Belbiţă (14-7-0)",
        "Prelim: Anthony Hernandez (9-2-0) vs. Marc-André Barriault (14-5-0)",
        "Prelim: Alen Amedovski (8-3-0) vs. Joseph Pyfer (9-2-0)",
        "Prelim: Mariya Agapova (10-3-0) vs. Gillian Robertson (10-7-0)",
        "Prelim: Tony Gravely (23-7-0) vs. Javid Basharat (12-0-0)"
      ]
    }
  },
  {
    "id": "tapology-89894",
    "promotion": "UFC",
    "sports": [
      "MMA"
    ],
    "mainCard": {
      "title": "UFC Fight Night: Dern vs. Yan",
      "time": "2022-10-01T23:00:00Z",
      "broadcasters": {
        "DAZN": {
        },
        "UFC_FIGHT_PASS": {
        }
      },
      "fightPass": {
        "id": 223405,
        "time": "2022-10-01T23:00:00Z",
        "title": "UFC Fight Night: Dern vs Xiaonan"
      }
    },
    "prelims": {
      "title": "UFC Fight Night: Prelims",
      "time": "2022-10-01T21:00:00Z",
      "broadcasters": {
        "UFC_FIGHT_PASS": {
        }
      },
      "fightPass": {
        "id": 223404,
        "time": "2022-10-01T21:00:00Z",
        "title": "UFC Fight Night: Dern vs Xiaonan Prelims"
      }
    },
    "tapology": {
      "id": 89894,
      "time": "2022-10-01T22:00:00Z",
      "title": "UFC Fight Night: Dern vs. Yan",
      "info": "Confirmed Upcoming MMA Event",
      "url": "https://www.tapology.com/fightcenter/events/89894-ufc-fight-night",
      "sports": [
        "MMA"
      ],
      "card": [
        "Main Event: Mackenzie Dern (12-2-0) vs. Xiaonan Yan (15-3-0)",
        "Main Card: Brendan Allen (19-5-0) vs. Krzysztof Jotko (24-5-0)",
        "Main Card: Randy Brown (15-4-0) vs. Francisco Trinaldo (28-8-0)",
        "Main Card: Cody Garbrandt (12-5-0) vs. Rani Yahya (28-10-1)",
        "Main Card: Raoni Barcelos (16-3-0) vs. Trevin Jones (13-8-0)",
        "Main Card: Jairzinho Rozenstruik (12-4-0) vs. Chris Daukaus (12-5-0)",
        "Main Card: Aleksei Oleinik (60-16-1) vs. Ilir Latifi (15-8-0)",
        "Prelim: Randy Costa (6-3-0) vs. Guido Cannetti (9-6-0)",
        "Prelim: Julija Stoliarenko (10-6-1) vs. Chelsea Chandler (4-1-0)",
        "Prelim: John Castañeda (19-5-0) vs. Daniel Santos (9-2-0)",
        "Prelim: Joaquim Silva (11-3-0) vs. Jesse Ronson (21-11-0)",
        "Prelim: Mike Davis (9-2-0) vs. Uros Medic (8-1-0)",
        "Prelim: Maxim Grishin (32-9-2) vs. Philipe Lins (15-5-0)",
        "Prelim: Jessica Penne (14-6-0) vs. Tabatha Ricci (7-1-0)"
      ]
    }
  },
  {
    "id": "tapology-90713",
    "promotion": "UFC",
    "sports": [
      "MMA"
    ],
    "mainCard": {
      "title": "UFC Fight Night",
      "time": "2022-10-15T22:00:00Z",
      "broadcasters": {
        "DAZN": {
        },
        "UFC_FIGHT_PASS": {
        }
      }
    },
    "prelims": {
      "title": "UFC Fight Night: Prelims",
      "broadcasters": {
        "UFC_FIGHT_PASS": {
        }
      }
    },
    "earlyPrelims": {
      "title": "UFC Fight Night: Early Prelims",
      "broadcasters": {
        "UFC_FIGHT_PASS": {
        }
      }
    },
    "tapology": {
      "id": 90713,
      "time": "2022-10-15T22:00:00Z",
      "title": "UFC Fight Night",
      "info": "Confirmed Upcoming MMA Event",
      "url": "https://www.tapology.com/fightcenter/events/90713-ufc-fight-night",
      "sports": [
        "MMA"
      ],
      "card": [
        "Main Card: Jonathan Martinez (16-4-0) vs. Cub Swanson (28-12-0)",
        "Main Card: Askar Askarov (14-1-1) vs. Brandon Royval (14-6-0)",
        "Main Card: Alexa Grasso (14-3-0) vs. Viviane Araujo (11-3-0)",
        "Main Card: Misha Cirkunov (15-8-0) vs. Alonzo Menifield (12-3-0)",
        "Prelim: Piera Rodriguez (8-0-0) vs. Sam Hughes (7-4-0)",
        "Prelim: C.J. Vergara (10-3-1) vs. Tatsuro Taira (11-0-0)",
        "Prelim: Mana Martinez (9-3-0) vs. Brandon Davis (14-9-0)",
        "Prelim: Mike Jackson (1-1-0) vs. Pete Rodriguez (4-1-0)",
        "Prelim: Raphael Assunção (27-9-0) vs. Victor Henry (22-5-0)",
        "Prelim: Melsik Baghdasaryan (7-1-0) vs. Joanderson Brito (13-3-1)"
      ]
    }
  },
  {
    "id": "tapology-87755",
    "promotion": "UFC",
    "sports": [
      "MMA"
    ],
    "tags": [
      "#UFC280"
    ],
    "mainCard": {
      "title": "UFC 280: Oliveira vs. Makhachev",
      "time": "2022-10-22T15:00:00Z",
      "broadcasters": {
        "DAZN": {
        },
        "UFC_FIGHT_PASS": {
        }
      },
      "fightPass": {
        "id": 223132,
        "time": "2022-10-22T15:00:00Z",
        "title": "UFC 280"
      }
    },
    "prelims": {
      "title": "UFC 280: Prelims",
      "broadcasters": {
        "UFC_FIGHT_PASS": {
        }
      }
    },
    "earlyPrelims": {
      "title": "UFC 280: Early Prelims",
      "broadcasters": {
        "UFC_FIGHT_PASS": {
        }
      }
    },
    "tapology": {
      "id": 87755,
      "time": "2022-10-22T14:00:00Z",
      "title": "UFC 280: Oliveira vs. Makhachev",
      "info": "Confirmed Upcoming MMA Event",
      "url": "https://www.tapology.com/fightcenter/events/87755-ufc-281",
      "sports": [
        "MMA"
      ],
      "card": [
        "Main Event: Charles Oliveira (33-8-0) vs. Islam Makhachev (22-1-0)",
        "Co-Main Event: Aljamain Sterling (21-3-0) vs. T.J. Dillashaw (17-4-0)",
        "Main Card: Belal Muhammad (21-3-0) vs. Sean Brady (15-0-0)",
        "Main Card: Petr Yan (16-3-0) vs. Sean O'Malley (15-1-0)",
        "Main Card: Beneil Dariush (21-4-1) vs. Mateusz Gamrot (21-1-0)",
        "Prelim: Zubaira Tukhugov (20-5-1) vs. Lucas Almeida (14-1-0)",
        "Prelim: Katlyn Chookagian (18-4-0) vs. Manon Fiorot (9-1-0)",
        "Prelim: Makhmud Muradov (25-7-0) vs. Caio Borralho (12-1-0)",
        "Prelim: Muhammad Mokaev (7-0-0) vs. Malcolm Gordon (14-5-0)",
        "Prelim: Volkan Oezdemir (18-6-0) vs. Nikita Krylov (28-9-0)",
        "Prelim: Abubakar Nurmagomedov (16-3-1) vs. Gadzhi Omargadzhiev (13-1-0)",
        "Prelim: Armen Petrosyan (7-2-0) vs. AJ Dobson (6-1-0)",
        "Prelim: Lina Länsberg (10-6-0) vs. Karol Rosa (15-4-0)",
        "Prelim: Hamdy Abdelwahab (4-0-0) vs. Parker Porter (13-7-0)",
        "Prelim: Magomed Mustafaev (14-4-0) vs. Jamie Mullarkey (15-5-0)"
      ]
    }
  },
  {
    "id": "tapology-91651",
    "promotion": "UFC",
    "sports": [
      "MMA"
    ],
    "mainCard": {
      "title": "UFC Fight Night",
      "time": "2022-10-29T22:00:00Z",
      "broadcasters": {
        "DAZN": {
        },
        "UFC_FIGHT_PASS": {
        }
      }
    },
    "prelims": {
      "title": "UFC Fight Night: Prelims",
      "broadcasters": {
        "UFC_FIGHT_PASS": {
        }
      }
    },
    "tapology": {
      "id": 91651,
      "time": "2022-10-29T22:00:00Z",
      "title": "UFC Fight Night",
      "info": "Confirmed Upcoming MMA Event",
      "url": "https://www.tapology.com/fightcenter/events/91651-ufc-fight-night",
      "sports": [
        "MMA"
      ],
      "card": [
        "Main Card: Edson Barboza (22-11-0) vs. Ilia Topuria (12-0-0)",
        "Main Card: Andrei Arlovski (34-20-0) vs. Marcos Rogério de Lima (19-8-1)",
        "Main Card: Dustin Jacoby (18-5-1) vs. Khalil Rountree (10-5-0)",
        "Main Card: Roman Dolidze (10-1-0) vs. Phil Hawes (12-3-0)",
        "Main Card: Tim Means (32-13-1) vs. Max Griffin (18-9-0)",
        "Prelim: Chase Hooper (11-2-1) vs. Steve Garcia (12-5-0)",
        "Prelim: Joseph Holmes (8-2-0) vs. Jun Yong Park (14-5-0)",
        "Prelim: Waldo Cortes-Acosta (7-0-0) vs. Jared Vanderaa (12-9-0)",
        "Prelim: Christian Rodriguez (7-1-0) vs. Garrett Armfield (8-3-0)",
        "Prelim: Tresean Gore (3-2-0) vs. Josh Fremd (9-3-0)",
        "Prelim: Cody Durden (13-4-1) vs. Kleydson Rodrigues (7-2-0)"
      ]
    }
  },
  {
    "id": "tapology-91921",
    "promotion": "UFC",
    "sports": [
      "MMA"
    ],
    "mainCard": {
      "title": "UFC Fight Night",
      "time": "2022-11-05T22:00:00Z",
      "broadcasters": {
        "DAZN": {
        },
        "UFC_FIGHT_PASS": {
        }
      }
    },
    "prelims": {
      "title": "UFC Fight Night: Prelims",
      "broadcasters": {
        "UFC_FIGHT_PASS": {
        }
      }
    },
    "tapology": {
      "id": 91921,
      "time": "2022-11-05T22:00:00Z",
      "title": "UFC Fight Night",
      "info": "Confirmed Upcoming MMA Event",
      "url": "https://www.tapology.com/fightcenter/events/91921-ufc-fight-night",
      "sports": [
        "MMA"
      ],
      "card": [
        "Main Card: Marina Rodriguez (16-1-2) vs. Amanda Lemos (12-2-1)",
        "Prelim: Mario Bautista (10-2-0) vs. Benito Lopez (10-1-0)",
        "Prelim: Tagir Ulanbekov (13-2-0) vs. Nate Maness (14-2-0)",
        "Prelim: Ramona Pascual (6-4-0) vs. Tamires Vidal (6-1-0)",
        "Prelim: Jinh Yu Frey (11-7-0) vs. Polyana Viana (12-5-0)",
        "Prelim: Johnny Munoz Jr. (11-2-0) vs. Liudvik Sholinian (9-2-1)",
        "Prelim: Jake Hadley (8-1-0) vs. Carlos Candelario (8-2-0)",
        "Prelim: Miranda Maverick (10-4-0) vs. Shanna Young (8-4-0)"
      ]
    }
  },
  {
    "id": "tapology-91828",
    "promotion": "UFC",
    "sports": [
      "MMA"
    ],
    "tags": [
      "#UFC281"
    ],
    "mainCard": {
      "title": "UFC 281",
      "time": "2022-11-13T03:00:00Z",
      "broadcasters": {
        "DAZN": {
        },
        "UFC_FIGHT_PASS": {
        }
      }
    },
    "prelims": {
      "title": "UFC 281: Prelims",
      "broadcasters": {
        "UFC_FIGHT_PASS": {
        }
      }
    },
    "earlyPrelims": {
      "title": "UFC 281: Early Prelims",
      "broadcasters": {
        "UFC_FIGHT_PASS": {
        }
      }
    },
    "tapology": {
      "id": 91828,
      "time": "2022-11-13T03:00:00Z",
      "title": "UFC 281: Adesanya vs. Pereira",
      "info": "Confirmed Upcoming MMA Event",
      "url": "https://www.tapology.com/fightcenter/events/91828-ufc-281",
      "sports": [
        "MMA"
      ],
      "card": [
        "Main Event: Israel Adesanya (23-1-0) vs. Alex Pereira (6-1-0)",
        "Co-Main Event: Carla Esparza (19-6-0) vs. Weili Zhang (22-3-0)",
        "Main Card: Dustin Poirier (28-7-0) vs. Michael Chandler (23-7-0)",
        "Main Card: Erin Blanchfield (9-1-0) vs. Molly McCann (13-4-0)",
        "Main Card: Dominick Reyes (12-3-0) vs. Ryan Spann (20-7-0)",
        "Prelim: Mike Trizano (9-3-0) vs. Seung Woo Choi (10-5-0)",
        "Prelim: Renato Moicano (16-5-1) vs. Brad Riddell (10-3-0)",
        "Prelim: Karolina Kowalkiewicz (13-7-0) vs. Silvana Gómez Juárez (11-4-0)",
        "Prelim: Ottman Azaitar (13-0-0) vs. Matt Frevola (9-3-1)",
        "Prelim: Dan Hooker (21-12-0) vs. Claudio Puelles (12-2-0)",
        "Prelim: Carlos Ulberg (6-1-0) vs. Nicolae Negumereanu (13-1-0)"
      ]
    }
  },
  {
    "id": "tapology-91976",
    "promotion": "UFC",
    "sports": [
      "MMA"
    ],
    "mainCard": {
      "title": "UFC Fight Night",
      "time": "2022-11-19T23:00:00Z",
      "broadcasters": {
        "DAZN": {
        },
        "UFC_FIGHT_PASS": {
        }
      }
    },
    "prelims": {
      "title": "UFC Fight Night: Prelims",
      "broadcasters": {
        "UFC_FIGHT_PASS": {
        }
      }
    },
    "tapology": {
      "id": 91976,
      "time": "2022-11-19T23:00:00Z",
      "title": "UFC Fight Night",
      "info": "Confirmed Upcoming MMA Event",
      "url": "https://www.tapology.com/fightcenter/events/91976-ufc-fight-night",
      "sports": [
        "MMA"
      ],
      "card": [
        "Main Card: Muslim Salikhov (18-3-0) vs. Andre Fialho (16-5-0)",
        "Prelim: Ricky Turcios (11-3-0) vs. Kevin Natividad (9-3-0)",
        "Prelim: Maria Oliveira (13-5-0) vs. Vanessa Demopoulos (8-4-0)",
        "Prelim: Jack Shore (16-1-0) vs. Kyler Phillips (10-2-0)",
        "Prelim: Cody Brundage (8-2-0) vs. Rodolfo Vieira (8-2-0)",
        "Prelim: Zhalgas Zhumagulov (14-7-0) vs. Charles Johnson (11-3-0)",
        "Prelim: Jennifer Maia (19-9-1) vs. Maryna Moroz (11-3-0)"
      ]
    }
  },
  {
    "id": "tapology-91801",
    "promotion": "UFC",
    "sports": [
      "MMA"
    ],
    "mainCard": {
      "title": "UFC Fight Night: Brunson vs. Hermansson",
      "time": "2022-12-03T23:00:00Z",
      "broadcasters": {
        "DAZN": {
        },
        "UFC_FIGHT_PASS": {
        }
      }
    },
    "prelims": {
      "title": "UFC Fight Night: Prelims",
      "broadcasters": {
        "UFC_FIGHT_PASS": {
        }
      }
    },
    "tapology": {
      "id": 91801,
      "time": "2022-12-03T23:00:00Z",
      "title": "UFC Fight Night: Brunson vs. Hermansson",
      "info": "Confirmed Upcoming MMA Event",
      "url": "https://www.tapology.com/fightcenter/events/91801-ufc-fight-night",
      "sports": [
        "MMA"
      ],
      "card": [
        "Main Event: Derek Brunson (23-8-0) vs. Jack Hermansson (23-7-0)",
        "Main Card: Tracy Cortez (10-1-0) vs. Amanda Ribas (11-3-0)",
        "Main Card: Matheus Nicolau (18-2-1) vs. Matt Schnell (16-7-0)",
        "Main Card: Clay Guida (37-22-0) vs. Scott Holtzman (14-5-0)",
        "Prelim: Eryk Anders (14-7-0) vs. Kyle Daukaus (11-3-0)",
        "Prelim: Francis Marshall (6-0-0) vs. Marcelo Rojo (16-8-0)",
        "Prelim: Natan Levy (7-1-0) vs. Genaro Valdéz (10-1-0)",
        "Prelim: Michael Johnson (20-18-0) vs. Marc Diakiese (16-5-0)",
        "Prelim: Angela Hill (14-12-0) vs. Emily Ducote (12-6-0)",
        "Prelim: Darren Elkins (27-10-0) vs. Jonathan Pearce (13-4-0)"
      ]
    }
  },
  {
    "id": "tapology-92214",
    "promotion": "UFC",
    "sports": [
      "MMA"
    ],
    "tags": [
      "#UFC282"
    ],
    "mainCard": {
      "title": "UFC 282",
      "time": "2022-12-10T23:00:00Z",
      "broadcasters": {
        "DAZN": {
        },
        "UFC_FIGHT_PASS": {
        }
      }
    },
    "prelims": {
      "title": "UFC 282: Prelims",
      "broadcasters": {
        "UFC_FIGHT_PASS": {
        }
      }
    },
    "earlyPrelims": {
      "title": "UFC 282: Early Prelims",
      "broadcasters": {
        "UFC_FIGHT_PASS": {
        }
      }
    },
    "tapology": {
      "id": 92214,
      "time": "2022-12-10T23:00:00Z",
      "title": "UFC 282",
      "info": "Confirmed Upcoming MMA Event",
      "url": "https://www.tapology.com/fightcenter/events/92214-ufc-282",
      "sports": [
        "MMA"
      ],
      "card": [
        "Main Card: Santiago Ponzinibbio (28-6-0) vs. Robbie Lawler (29-16-0)",
        "Main Card: Billy Quarantillo (16-4-0) vs. Alexander Hernandez (13-5-0)",
        "Prelim: Edmen Shahbazyan (11-3-0) vs. Dalcha Lungiambula (11-5-0)"
      ]
    }
  },
  {
    "id": "tapology-92365",
    "promotion": "UFC",
    "sports": [
      "MMA"
    ],
    "mainCard": {
      "title": "UFC Fight Night",
      "time": "2022-12-17T23:00:00Z",
      "broadcasters": {
        "DAZN": {
        },
        "UFC_FIGHT_PASS": {
        }
      }
    },
    "prelims": {
      "title": "UFC Fight Night: Prelims",
      "broadcasters": {
        "UFC_FIGHT_PASS": {
        }
      }
    },
    "earlyPrelims": {
      "title": "UFC Fight Night: Early Prelims",
      "broadcasters": {
        "UFC_FIGHT_PASS": {
        }
      }
    },
    "tapology": {
      "id": 92365,
      "time": "2022-12-17T23:00:00Z",
      "title": "UFC Fight Night",
      "info": "Confirmed Upcoming MMA Event",
      "url": "https://www.tapology.com/fightcenter/events/92365-ufc-fight-night",
      "sports": [
        "MMA"
      ],
      "card": [
        "Main Card: Alex Perez (24-7-0) vs. Amir Albazi (15-1-0)",
        "Prelim: Julian Marquez (9-3-0) vs. Deron Winn (7-3-0)",
        "Prelim: Tafon Nchukwi (6-3-0) vs. Jamal Pogues (9-3-0)",
        "Prelim: Sergey Morozov (18-5-0) vs. Journey Newson (10-3-0)",
        "Prelim: Bruno Silva (22-8-0) vs. Albert Duraev (15-4-0)"
      ]
    }
  },
  {
    "id": "tapology-92055",
    "promotion": "UFC",
    "sports": [
      "MMA"
    ],
    "tags": [
      "#UFC283"
    ],
    "mainCard": {
      "title": "UFC 283",
      "time": "2023-01-21T23:00:00Z",
      "broadcasters": {
        "DAZN": {
        },
        "UFC_FIGHT_PASS": {
        }
      }
    },
    "prelims": {
      "title": "UFC 283: Prelims",
      "broadcasters": {
        "UFC_FIGHT_PASS": {
        }
      }
    },
    "earlyPrelims": {
      "title": "UFC 283: Early Prelims",
      "broadcasters": {
        "UFC_FIGHT_PASS": {
        }
      }
    },
    "tapology": {
      "id": 92055,
      "time": "2023-01-21T23:00:00Z",
      "title": "UFC 283",
      "info": "Confirmed Upcoming Event",
      "url": "https://www.tapology.com/fightcenter/events/92055-ufc-283"
    }
  }
]