[{"id":"2024-11-one-fight-night-28","title":"ONE Fight Night 28","time":"2024-11-09T01:00:00Z","until":"2024-11-09T04:00:00Z","promotion":"ONE","sports":["MMA","KICKBOXING","MUAY_THAI"],"links":["https://www.tapology.com/fightcenter/events/109351-one-fight-night-28"],"broadcasters":{"YOUTUBE":{"free":true}}},{"id":"2024-11-we-love-mma-75","title":"We Love MMA 75","time":"2024-11-23T18:00:00Z","until":"2024-11-23T21:00:00Z","promotion":"WLMMA_DE","sports":["MMA"],"links":["https://welovemma.de/we-love-mma-77/","https://www.tapology.com/fightcenter/events/110125-we-love-mma-75"]}]