[
  {
    "id": "XiKY3r3Kucw",
    "time": "2022-11-12T00:00:00Z",
    "title": "LIVE: PFL International Qualifier Series 2022 | Brasilien | 12.11. - FIGHTING",
    "url": "https://www.youtube.com/watch?v=XiKY3r3Kucw",
    "tags": [
      "#MMA",
      "#Fighting",
      "#Kampfsport"
    ]
  },
  {
    "id": "OI900rDqF90",
    "time": "2022-11-12T18:15:00Z",
    "title": "LIVE: Enfusion #115 | 12.11. - FIGHTING",
    "url": "https://www.youtube.com/watch?v=OI900rDqF90"
  },
  {
    "id": "l51FTyTAbcY",
    "time": "2022-11-19T17:00:00Z",
    "title": "LIVE: Glory 82 | Nabiyev vs Semeleer | 19.11. - FIGHTING",
    "url": "https://www.youtube.com/watch?v=l51FTyTAbcY",
    "tags": [
      "#MMA",
      "#Fighting",
      "#Kampfsport"
    ]
  },
  {
    "id": "9S50rjfNSRA",
    "time": "2022-11-19T18:00:00Z",
    "title": "LIVE: Enfusion #116 | 19.11. | Kickboxen - FIGHTING",
    "url": "https://www.youtube.com/watch?v=9S50rjfNSRA"
  },
  {
    "id": "Pobo9hiszr4",
    "time": "2022-11-26T00:00:00Z",
    "title": "LIVE: PFL FINALE | 26.11. - FIGHTING",
    "url": "https://www.youtube.com/watch?v=Pobo9hiszr4",
    "tags": [
      "#MMA",
      "#Fighting",
      "#Kampfsport"
    ]
  },
  {
    "id": "QVBtFvbKquw",
    "time": "2022-11-26T09:30:00Z",
    "title": "LIVE: Brave 66 | 26.11. | MMA - FIGHTING",
    "url": "https://www.youtube.com/watch?v=QVBtFvbKquw",
    "tags": [
      "#MMA",
      "#Fighting",
      "#Kampfsport"
    ]
  },
  {
    "id": "8YJE12SgCBE",
    "time": "2022-11-26T11:00:00Z",
    "title": "FREE: Deutsche Meisterschaft | GEMMAF | MMA | 26.11. - FIGHTING",
    "url": "https://www.youtube.com/watch?v=8YJE12SgCBE",
    "tags": [
      "#MMA",
      "#Fighting",
      "#Kampfsport"
    ]
  },
  {
    "id": "w-68jCgTttI",
    "time": "2022-12-16T17:00:00Z",
    "title": "FREE: NFC Contenders | 16.12. | Düsseldorf - FIGHTING",
    "url": "https://www.youtube.com/watch?v=w-68jCgTttI",
    "tags": [
      "#MMA",
      "#Fighting",
      "#Kampfsport"
    ]
  },
  {
    "id": "1IdEZCty6Vk",
    "time": "2022-12-17T17:00:00Z",
    "title": "LIVE: NFC 11| Islam Dulatov vs Florim Zendeli | 17.12. - FIGHTING",
    "url": "https://www.youtube.com/watch?v=1IdEZCty6Vk",
    "tags": [
      "#MMA",
      "#Fighting",
      "#Kampfsport"
    ]
  }
]