[
  {
    "id": "gMDImea4fhY",
    "time": "2025-05-28T15:00:00Z",
    "title": "Daily Dose of Knockouts 👊",
    "url": "https://www.youtube.com/watch?v=gMDImea4fhY",
    "tags": [
      "#UFC",
      "#highlights",
      "#knockout"
    ]
  },
  {
    "id": "M97cavlJF3Y",
    "time": "2025-06-01T04:00:00Z",
    "title": "🔴 UFC Vegas 107: Post-Fight Press Conference",
    "url": "https://www.youtube.com/watch?v=M97cavlJF3Y",
    "tags": [
      "#UFC",
      "#ufcvegas107",
      "#pressconference"
    ]
  }
]